canmatrix_webapp/__init__.py
canmatrix_webapp/run_web_app.py
canmatrix_webapp/web_app.py
canmatrix_webapp-25.0.0.dist-info/WHEEL
canmatrix_webapp-25.0.0.dist-info/METADATA
canmatrix_webapp-25.0.0.dist-info/RECORD
