Metadata-Version: 2.3
Name: canmatrix-webapp
Version: 25.0.0
Summary: streamlit webapp for canmatrix python package
Keywords: python,canmatrix,streamlit,webapp
Author: chaitu-ycr
Author-email: chaitu-ycr <chaitu.ycr@gmail.com>
License: MIT License
Classifier: Programming Language :: Python :: 3
Classifier: License :: OSI Approved :: MIT License
Classifier: Operating System :: Microsoft :: Windows
Requires-Dist: canmatrix[arxml,fibex,kcd,xls,xlsx]
Requires-Dist: streamlit
Requires-Python: >=3.10, <=3.14
Project-URL: documentation, https://chaitu-ycr.github.io/automotive-test-kit/packages/canmatrix_webapp
Project-URL: homepage, https://github.com/chaitu-ycr/automotive-test-kit/tree/main/packages/canmatrix_webapp
Project-URL: repository, https://github.com/chaitu-ycr/automotive-test-kit
